deal_image_lib/__init__.py
deal_image_lib/core.py
deal_image_lib-0.1.0.dist-info/METADATA
deal_image_lib-0.1.0.dist-info/WHEEL
deal_image_lib-0.1.0.dist-info/top_level.txt
deal_image_lib-0.1.0.dist-info/RECORD
